docs/source/conf.py
examples/dev_environment/grader_service_config.py
examples/dev_environment/grader_service_config_test.py
examples/dev_environment/jupyter_notebook_config.py
examples/dev_environment/jupyterhub_config.py
examples/dev_environment/jupyterhub_config_test.py
examples/docker_compose/grader_service_config.py
examples/docker_compose/jupyterhub_config.py
grader_service/__init__.py
grader_service/_version.py
grader_service/main.py
grader_service/registry.py
grader_service/request.py
grader_service/server.py
grader_service/utils.py
grader_service/api/__init__.py
grader_service/api/typing_utils.py
grader_service/api/util.py
grader_service/api/models/__init__.py
grader_service/api/models/assignment.py
grader_service/api/models/assignment_detail.py
grader_service/api/models/assignment_settings.py
grader_service/api/models/auto_status.py
grader_service/api/models/base_model.py
grader_service/api/models/error_message.py
grader_service/api/models/feedback_status.py
grader_service/api/models/lecture.py
grader_service/api/models/manual_status.py
grader_service/api/models/remote_file_status.py
grader_service/api/models/submission.py
grader_service/api/models/submission_period.py
grader_service/api/models/user.py
grader_service/api/models/user_submissions_inner.py
grader_service/auth/__init__.py
grader_service/auth/auth.py
grader_service/auth/crypto.py
grader_service/auth/dummy.py
grader_service/auth/local.py
grader_service/auth/login.py
grader_service/auth/oauth2.py
grader_service/auth/pam.py
grader_service/auth/token.py
grader_service/auth/lti13/__init__.py
grader_service/auth/lti13/auth.py
grader_service/auth/lti13/constants.py
grader_service/auth/lti13/error.py
grader_service/auth/lti13/handlers.py
grader_service/auth/lti13/validator.py
grader_service/autograding/__init__.py
grader_service/autograding/git_manager.py
grader_service/autograding/local_feedback.py
grader_service/autograding/local_grader.py
grader_service/autograding/utils.py
grader_service-0.11.2.dist-info/licenses/LICENSE
grader_service-0.11.2.dist-info/licenses/NOTICE
grader_service-0.11.2.dist-info/METADATA
grader_service-0.11.2.dist-info/WHEEL
grader_service-0.11.2.dist-info/entry_points.txt
grader_service-0.11.2.dist-info/top_level.txt
grader_service-0.11.2.dist-info/RECORD
